arcane/tasks.py
arcane_tasks-0.7.1.dist-info/METADATA
arcane_tasks-0.7.1.dist-info/WHEEL
arcane_tasks-0.7.1.dist-info/RECORD
